[
  {
    "Sn": "S.N.",
    "Traded_Companies": "Traded Companies",
    "No_Of_Transaction": "No. Of Transaction",
    "Max_Price": "Max Price",
    "Min_Price": "Min Price",
    "Closing_Price": "Closing Price",
    "Traded_Shares": "Traded Shares",
    "Amount": "Amount",
    "Previous_Closing": "Previous Closing",
    "Difference_Rs": "Difference Rs."
  },
  {
    "Sn": "201",
    "Traded_Companies": "Support Microfinance Bittiya Sanstha Ltd.",
    "No_Of_Transaction": "55",
    "Max_Price": "2535.00",
    "Min_Price": "2450.00",
    "Closing_Price": "2495.00",
    "Traded_Shares": "1344.00",
    "Amount": "3352330.00",
    "Previous_Closing": "2495.00",
    "Difference_Rs": "0.00  "
  },
  {
    "Sn": "202",
    "Traded_Companies": "Surya Life Insurance Company Limited",
    "No_Of_Transaction": "643",
    "Max_Price": "1029.00",
    "Min_Price": "1001.00",
    "Closing_Price": "1007.00",
    "Traded_Shares": "82110.00",
    "Amount": "83036265.00",
    "Previous_Closing": "998.00",
    "Difference_Rs": "9.00  "
  },
  {
    "Sn": "203",
    "Traded_Companies": "Suryodaya Laghubitta Bittiya Sanstha Ltd.",
    "No_Of_Transaction": "59",
    "Max_Price": "1810.00",
    "Min_Price": "1750.00",
    "Closing_Price": "1750.00",
    "Traded_Shares": "2870.00",
    "Amount": "5090449.00",
    "Previous_Closing": "1775.00",
    "Difference_Rs": "-25.00  "
  },
  {
    "Sn": "204",
    "Traded_Companies": "Swabalamban Laghubitta Bittiya Sanstha Limited",
    "No_Of_Transaction": "128",
    "Max_Price": "1775.00",
    "Min_Price": "1730.00",
    "Closing_Price": "1735.00",
    "Traded_Shares": "8843.00",
    "Amount": "15540139.00",
    "Previous_Closing": "1741.00",
    "Difference_Rs": "-6.00  "
  },
  {
    "Sn": "205",
    "Traded_Companies": "Swabhimaan Laghubitta Bittiya Sanstha Limited",
    "No_Of_Transaction": "100",
    "Max_Price": "2663.00",
    "Min_Price": "2558.00",
    "Closing_Price": "2567.00",
    "Traded_Shares": "3226.00",
    "Amount": "8397613.00",
    "Previous_Closing": "2515.00",
    "Difference_Rs": "52.00  "
  },
  {
    "Sn": "206",
    "Traded_Companies": "Swarojgar Laghu Bitta Bikas Bank Ltd.",
    "No_Of_Transaction": "177",
    "Max_Price": "1545.00",
    "Min_Price": "1503.00",
    "Closing_Price": "1515.00",
    "Traded_Shares": "21549.00",
    "Amount": "32749832.00",
    "Previous_Closing": "1513.00",
    "Difference_Rs": "2.00  "
  },
  {
    "Sn": "207",
    "Traded_Companies": "Synergy Power Development Ltd.",
    "No_Of_Transaction": "793",
    "Max_Price": "443.00",
    "Min_Price": "411.00",
    "Closing_Price": "414.00",
    "Traded_Shares": "164034.00",
    "Amount": "69536298.00",
    "Previous_Closing": "429.00",
    "Difference_Rs": "-15.00  "
  },
  {
    "Sn": "208",
    "Traded_Companies": "Taragaon Regency Hotel Limited",
    "No_Of_Transaction": "182",
    "Max_Price": "358.00",
    "Min_Price": "327.00",
    "Closing_Price": "341.00",
    "Traded_Shares": "17689.00",
    "Amount": "6070441.00",
    "Previous_Closing": "344.00",
    "Difference_Rs": "-3.00  "
  },
  {
    "Sn": "209",
    "Traded_Companies": "Unilever Nepal Limited",
    "No_Of_Transaction": "9",
    "Max_Price": "20200.00",
    "Min_Price": "19826.00",
    "Closing_Price": "19826.00",
    "Traded_Shares": "95.00",
    "Amount": "1897670.00",
    "Previous_Closing": "20000.00",
    "Difference_Rs": "-174.00  "
  },
  {
    "Sn": "210",
    "Traded_Companies": "Union Hydropower Limited",
    "No_Of_Transaction": "1077",
    "Max_Price": "310.00",
    "Min_Price": "281.00",
    "Closing_Price": "292.00",
    "Traded_Shares": "225284.00",
    "Amount": "67856757.00",
    "Previous_Closing": "282.00",
    "Difference_Rs": "10.00  "
  },
  {
    "Sn": "211",
    "Traded_Companies": "United IDI Mardi RB Hydropower Limited.",
    "No_Of_Transaction": "442",
    "Max_Price": "541.00",
    "Min_Price": "506.00",
    "Closing_Price": "541.00",
    "Traded_Shares": "31370.00",
    "Amount": "16425962.00",
    "Previous_Closing": "530.00",
    "Difference_Rs": "11.00  "
  },
  {
    "Sn": "212",
    "Traded_Companies": "United Insurance Co. (Nepal) Ltd.",
    "No_Of_Transaction": "517",
    "Max_Price": "793.00",
    "Min_Price": "732.00",
    "Closing_Price": "765.00",
    "Traded_Shares": "67634.00",
    "Amount": "52550779.00",
    "Previous_Closing": "770.00",
    "Difference_Rs": "-5.00  "
  },
  {
    "Sn": "213",
    "Traded_Companies": "United Modi Hydropower Ltd.",
    "No_Of_Transaction": "1106",
    "Max_Price": "357.00",
    "Min_Price": "331.00",
    "Closing_Price": "339.00",
    "Traded_Shares": "239858.00",
    "Amount": "82457082.00",
    "Previous_Closing": "349.00",
    "Difference_Rs": "-10.00  "
  },
  {
    "Sn": "214",
    "Traded_Companies": "UNIVERSAL POWER COMPANY LTD",
    "No_Of_Transaction": "950",
    "Max_Price": "302.00",
    "Min_Price": "279.00",
    "Closing_Price": "282.00",
    "Traded_Shares": "179025.00",
    "Amount": "51457441.00",
    "Previous_Closing": "293.00",
    "Difference_Rs": "-11.00  "
  },
  {
    "Sn": "215",
    "Traded_Companies": "Unnati Sahakarya Laghubitta Bittiya Sanstha Limited",
    "No_Of_Transaction": "24",
    "Max_Price": "2330.00",
    "Min_Price": "2279.00",
    "Closing_Price": "2279.00",
    "Traded_Shares": "1154.00",
    "Amount": "2649631.00",
    "Previous_Closing": "2286.00",
    "Difference_Rs": "-7.00  "
  },
  {
    "Sn": "216",
    "Traded_Companies": "Upper Tamakoshi Hydropower Ltd",
    "No_Of_Transaction": "1339",
    "Max_Price": "797.00",
    "Min_Price": "776.00",
    "Closing_Price": "777.00",
    "Traded_Shares": "170731.00",
    "Amount": "133386866.00",
    "Previous_Closing": "786.00",
    "Difference_Rs": "-9.00  "
  },
  {
    "Sn": "217",
    "Traded_Companies": "Vijaya laghubitta Bittiya Sanstha Ltd.",
    "No_Of_Transaction": "84",
    "Max_Price": "1835.00",
    "Min_Price": "1795.00",
    "Closing_Price": "1807.00",
    "Traded_Shares": "3512.00",
    "Amount": "6393415.00",
    "Previous_Closing": "1795.00",
    "Difference_Rs": "12.00  "
  },
  {
    "Sn": "218",
    "Traded_Companies": "Womi Microfinance Bittiya Sanstha Ltd.",
    "No_Of_Transaction": "96",
    "Max_Price": "1660.00",
    "Min_Price": "1630.00",
    "Closing_Price": "1645.00",
    "Traded_Shares": "6745.00",
    "Amount": "11116180.00",
    "Previous_Closing": "1632.00",
    "Difference_Rs": "10.00  "
  }
]