[
  {
    "Sn": "S.N.",
    "Traded_Companies": "Traded Companies",
    "No_Of_Transaction": "No. Of Transaction",
    "Max_Price": "Max Price",
    "Min_Price": "Min Price",
    "Closing_Price": "Closing Price",
    "Traded_Shares": "Traded Shares",
    "Amount": "Amount",
    "Previous_Closing": "Previous Closing",
    "Difference_Rs": "Difference Rs."
  },
  {
    "Sn": "121",
    "Traded_Companies": "Nepal Credit And Commercial Bank Limited",
    "No_Of_Transaction": "961",
    "Max_Price": "369.00",
    "Min_Price": "356.00",
    "Closing_Price": "363.00",
    "Traded_Shares": "378252.00",
    "Amount": "136476657.00",
    "Previous_Closing": "356.00",
    "Difference_Rs": "6.00  "
  },
  {
    "Sn": "122",
    "Traded_Companies": "Nepal Doorsanchar Comapany Limited",
    "No_Of_Transaction": "1003",
    "Max_Price": "1328.00",
    "Min_Price": "1275.00",
    "Closing_Price": "1276.00",
    "Traded_Shares": "90914.00",
    "Amount": "117319854.00",
    "Previous_Closing": "1277.00",
    "Difference_Rs": "-1.00  "
  },
  {
    "Sn": "123",
    "Traded_Companies": "Nepal Finance Ltd.",
    "No_Of_Transaction": "743",
    "Max_Price": "458.00",
    "Min_Price": "424.00",
    "Closing_Price": "426.00",
    "Traded_Shares": "113472.00",
    "Amount": "49880561.00",
    "Previous_Closing": "425.00",
    "Difference_Rs": "1.00  "
  },
  {
    "Sn": "124",
    "Traded_Companies": "Nepal Hydro Developers Ltd.",
    "No_Of_Transaction": "126",
    "Max_Price": "479.00",
    "Min_Price": "452.00",
    "Closing_Price": "460.00",
    "Traded_Shares": "11251.00",
    "Amount": "5218737.00",
    "Previous_Closing": "470.00",
    "Difference_Rs": "-10.00  "
  },
  {
    "Sn": "125",
    "Traded_Companies": "Nepal Infrastructure Bank Limited",
    "No_Of_Transaction": "5473",
    "Max_Price": "540.00",
    "Min_Price": "525.00",
    "Closing_Price": "533.00",
    "Traded_Shares": "618859.00",
    "Amount": "331386774.00",
    "Previous_Closing": "524.00",
    "Difference_Rs": "9.00  "
  },
  {
    "Sn": "126",
    "Traded_Companies": "Nepal Insurance Co. Ltd.",
    "No_Of_Transaction": "356",
    "Max_Price": "868.00",
    "Min_Price": "814.00",
    "Closing_Price": "840.00",
    "Traded_Shares": "51605.00",
    "Amount": "43894311.00",
    "Previous_Closing": "854.00",
    "Difference_Rs": "-14.00  "
  },
  {
    "Sn": "127",
    "Traded_Companies": "Nepal Life Insurance Co. Ltd.",
    "No_Of_Transaction": "768",
    "Max_Price": "2138.00",
    "Min_Price": "2082.00",
    "Closing_Price": "2088.00",
    "Traded_Shares": "47425.00",
    "Amount": "99359042.00",
    "Previous_Closing": "2098.00",
    "Difference_Rs": "-10.00  "
  },
  {
    "Sn": "128",
    "Traded_Companies": "Nepal Reinsurance Company Limited",
    "No_Of_Transaction": "5243",
    "Max_Price": "1855.00",
    "Min_Price": "1760.00",
    "Closing_Price": "1765.00",
    "Traded_Shares": "571115.00",
    "Amount": "1027027287.00",
    "Previous_Closing": "1790.00",
    "Difference_Rs": "-25.00  "
  },
  {
    "Sn": "129",
    "Traded_Companies": "Nepal SBI Bank Limited",
    "No_Of_Transaction": "537",
    "Max_Price": "419.00",
    "Min_Price": "407.00",
    "Closing_Price": "416.00",
    "Traded_Shares": "116726.00",
    "Amount": "48334459.00",
    "Previous_Closing": "408.00",
    "Difference_Rs": "8.00  "
  },
  {
    "Sn": "130",
    "Traded_Companies": "Nerude Laghubita Bikas Bank Limited",
    "No_Of_Transaction": "194",
    "Max_Price": "1723.00",
    "Min_Price": "1667.00",
    "Closing_Price": "1667.00",
    "Traded_Shares": "28185.00",
    "Amount": "47631318.00",
    "Previous_Closing": "1670.00",
    "Difference_Rs": "-3.00  "
  },
  {
    "Sn": "131",
    "Traded_Companies": "Ngadi Group Power Ltd.",
    "No_Of_Transaction": "446",
    "Max_Price": "400.00",
    "Min_Price": "368.00",
    "Closing_Price": "370.00",
    "Traded_Shares": "76473.00",
    "Amount": "28960037.00",
    "Previous_Closing": "384.00",
    "Difference_Rs": "-14.00  "
  },
  {
    "Sn": "132",
    "Traded_Companies": "NIBL Pragati Fund",
    "No_Of_Transaction": "35",
    "Max_Price": "14.23",
    "Min_Price": "13.86",
    "Closing_Price": "13.96",
    "Traded_Shares": "105775.00",
    "Amount": "1493323.17",
    "Previous_Closing": "14.04",
    "Difference_Rs": "-0.08  "
  },
  {
    "Sn": "133",
    "Traded_Companies": "NIBL Samriddhi Fund 1",
    "No_Of_Transaction": "18",
    "Max_Price": "14.79",
    "Min_Price": "14.30",
    "Closing_Price": "14.56",
    "Traded_Shares": "35310.00",
    "Amount": "514297.38",
    "Previous_Closing": "14.50",
    "Difference_Rs": "0.06  "
  },
  {
    "Sn": "134",
    "Traded_Companies": "NIC Asia Balanced Fund",
    "No_Of_Transaction": "53",
    "Max_Price": "13.13",
    "Min_Price": "12.81",
    "Closing_Price": "13.00",
    "Traded_Shares": "97350.00",
    "Amount": "1263850.50",
    "Previous_Closing": "12.80",
    "Difference_Rs": "0.20  "
  },
  {
    "Sn": "135",
    "Traded_Companies": "NIC Asia Bank Ltd.",
    "No_Of_Transaction": "1337",
    "Max_Price": "935.00",
    "Min_Price": "905.00",
    "Closing_Price": "918.00",
    "Traded_Shares": "246324.00",
    "Amount": "226675641.00",
    "Previous_Closing": "900.00",
    "Difference_Rs": "18.00  "
  },
  {
    "Sn": "136",
    "Traded_Companies": "NIC Asia Growth Fund",
    "No_Of_Transaction": "30",
    "Max_Price": "14.19",
    "Min_Price": "14.00",
    "Closing_Price": "14.03",
    "Traded_Shares": "285700.00",
    "Amount": "4022170.00",
    "Previous_Closing": "13.95",
    "Difference_Rs": "0.08  "
  },
  {
    "Sn": "137",
    "Traded_Companies": "NIC ASIA Laghubitta Bittiya Sanstha Limited",
    "No_Of_Transaction": "1010",
    "Max_Price": "1725.00",
    "Min_Price": "1649.00",
    "Closing_Price": "1649.00",
    "Traded_Shares": "25530.00",
    "Amount": "42426662.00",
    "Previous_Closing": "1643.00",
    "Difference_Rs": "6.00  "
  },
  {
    "Sn": "138",
    "Traded_Companies": "Nirdhan Utthan Laghubitta Bittiya Sanstha Limited",
    "No_Of_Transaction": "451",
    "Max_Price": "1742.00",
    "Min_Price": "1605.00",
    "Closing_Price": "1700.00",
    "Traded_Shares": "38646.00",
    "Amount": "66548948.00",
    "Previous_Closing": "1675.00",
    "Difference_Rs": "25.00  "
  },
  {
    "Sn": "139",
    "Traded_Companies": "NLG Insurance Company Ltd.",
    "No_Of_Transaction": "831",
    "Max_Price": "1238.00",
    "Min_Price": "1197.00",
    "Closing_Price": "1224.00",
    "Traded_Shares": "159195.00",
    "Amount": "192925835.00",
    "Previous_Closing": "1190.00",
    "Difference_Rs": "34.00  "
  },
  {
    "Sn": "140",
    "Traded_Companies": "NMB Microfinance Bittiya Sanstha Ltd.",
    "No_Of_Transaction": "170",
    "Max_Price": "1521.00",
    "Min_Price": "1480.00",
    "Closing_Price": "1499.00",
    "Traded_Shares": "16499.00",
    "Amount": "24785299.00",
    "Previous_Closing": "1475.00",
    "Difference_Rs": "24.00  "
  }
]